openlibrary.py
openlibrary-0.0.1.dist-info/top_level.txt
openlibrary-0.0.1.dist-info/metadata.json
openlibrary-0.0.1.dist-info/DESCRIPTION.rst
openlibrary-0.0.1.dist-info/METADATA
openlibrary-0.0.1.dist-info/WHEEL
openlibrary-0.0.1.dist-info/RECORD
