Metadata-Version: 2.0
Name: openlibrary
Version: 0.0.1
Summary: A Python Interface for the OpenLibrary API
Home-page: https://github.com/kalikaneko/pyopenlibrary
Author: Kali Kaneko
Author-email: kali@futeisha.org
License: GPLv3+
Download-URL: https://github.com/kalikaneko/pyopenlibrary/archive/master.zip
Platform: Linux
Platform: BSD
Platform: OSX
Platform: Windows
Classifier: Development Status :: 5 - Production/Stable
Classifier: Intended Audience :: Developers
Classifier: License :: OSI Approved :: GNU General Public License v3 or later (GPLv3+)
Classifier: Programming Language :: Python
Classifier: Programming Language :: Python :: 2
Classifier: Programming Language :: Python :: 3
Classifier: Programming Language :: Python :: 2.6
Classifier: Programming Language :: Python :: 2.7
Classifier: Programming Language :: Python :: 3.3
Classifier: Programming Language :: Python :: 3.4
Classifier: Topic :: Software Development :: Libraries :: Python Modules
Classifier: Topic :: Utilities
